{
  "$encoding": "utf-8",
  "$schema": "https://github.com/alxroyer/scenario/blob/v0.2.2/schemas/scenario-report.schema.json",
  "$version": "0.2.2",
  "name": "demo/commutativeadditions.py",
  "href": "../../demo/commutativeadditions.py",
  "attributes": {
    "TITLE": "Commutative additions",
    "DESCRIPTION": "Call the CommutativeAddition scenario with different inputs."
  },
  "reqs": [],
  "steps": [
    {
      "location": "demo/commutativeadditions.py:20:CommutativeAdditions.step010",
      "description": "Both positive members",
      "reqs": [],
      "actions-results": [
        {
          "type": "ACTION",
          "description": "Launch the CommutativeAddition scenario with 4 and 5 for inputs.",
          "executions": [
            {
              "time": {
                "start": "YYYY-MM-DDTHH:MM:SS.mmmmmm+HH:MM",
                "end": "YYYY-MM-DDTHH:MM:SS.mmmmmm+HH:MM",
                "elapsed": SSS.mmmmmm
              },
              "evidence": [],
              "errors": [],
              "warnings": [],
              "subscenarios": [
                {
                  "name": "demo/commutativeaddition.py",
                  "href": "../../demo/commutativeaddition.py",
                  "attributes": {
                    "TITLE": "Commutative addition",
                    "DESCRIPTION": "Addition of two members, swapping orders."
                  },
                  "reqs": [],
                  "steps": [
                    {
                      "location": "demo/commutativeaddition.py:20:CommutativeAddition.step000",
                      "description": "Initial conditions",
                      "reqs": [],
                      "actions-results": [
                        {
                          "type": "ACTION",
                          "description": "Let a = 4, and b = 5",
                          "executions": [
                            {
                              "time": {
                                "start": "YYYY-MM-DDTHH:MM:SS.mmmmmm+HH:MM",
                                "end": "YYYY-MM-DDTHH:MM:SS.mmmmmm+HH:MM",
                                "elapsed": SSS.mmmmmm
                              },
                              "evidence": [
                                "a = 4",
                                "b = 5"
                              ],
                              "errors": [],
                              "warnings": [],
                              "subscenarios": []
                            }
                          ]
                        }
                      ],
                      "executions": [
                        {
                          "number": 1,
                          "time": {
                            "start": "YYYY-MM-DDTHH:MM:SS.mmmmmm+HH:MM",
                            "end": "YYYY-MM-DDTHH:MM:SS.mmmmmm+HH:MM",
                            "elapsed": SSS.mmmmmm
                          },
                          "errors": [],
                          "warnings": []
                        }
                      ]
                    },
                    {
                      "location": "demo/commutativeaddition.py:27:CommutativeAddition.step010",
                      "description": "a + b",
                      "reqs": [],
                      "actions-results": [
                        {
                          "type": "ACTION",
                          "description": "Compute (a + b) and store the result as result1.",
                          "executions": [
                            {
                              "time": {
                                "start": "YYYY-MM-DDTHH:MM:SS.mmmmmm+HH:MM",
                                "end": "YYYY-MM-DDTHH:MM:SS.mmmmmm+HH:MM",
                                "elapsed": SSS.mmmmmm
                              },
                              "evidence": [
                                "result1 = 9"
                              ],
                              "errors": [],
                              "warnings": [],
                              "subscenarios": []
                            }
                          ]
                        }
                      ],
                      "executions": [
                        {
                          "number": 2,
                          "time": {
                            "start": "YYYY-MM-DDTHH:MM:SS.mmmmmm+HH:MM",
                            "end": "YYYY-MM-DDTHH:MM:SS.mmmmmm+HH:MM",
                            "elapsed": SSS.mmmmmm
                          },
                          "errors": [],
                          "warnings": []
                        }
                      ]
                    },
                    {
                      "location": "demo/commutativeaddition.py:34:CommutativeAddition.step020",
                      "description": "b + a",
                      "reqs": [],
                      "actions-results": [
                        {
                          "type": "ACTION",
                          "description": "Compute (b + a) and store the result as result2.",
                          "executions": [
                            {
                              "time": {
                                "start": "YYYY-MM-DDTHH:MM:SS.mmmmmm+HH:MM",
                                "end": "YYYY-MM-DDTHH:MM:SS.mmmmmm+HH:MM",
                                "elapsed": SSS.mmmmmm
                              },
                              "evidence": [
                                "result2 = 9"
                              ],
                              "errors": [],
                              "warnings": [],
                              "subscenarios": []
                            }
                          ]
                        }
                      ],
                      "executions": [
                        {
                          "number": 3,
                          "time": {
                            "start": "YYYY-MM-DDTHH:MM:SS.mmmmmm+HH:MM",
                            "end": "YYYY-MM-DDTHH:MM:SS.mmmmmm+HH:MM",
                            "elapsed": SSS.mmmmmm
                          },
                          "errors": [],
                          "warnings": []
                        }
                      ]
                    },
                    {
                      "location": "demo/commutativeaddition.py:41:CommutativeAddition.step030",
                      "description": "Check",
                      "reqs": [],
                      "actions-results": [
                        {
                          "type": "ACTION",
                          "description": "Compare result1 and result2.",
                          "executions": [
                            {
                              "time": {
                                "start": "YYYY-MM-DDTHH:MM:SS.mmmmmm+HH:MM",
                                "end": "YYYY-MM-DDTHH:MM:SS.mmmmmm+HH:MM",
                                "elapsed": SSS.mmmmmm
                              },
                              "evidence": [],
                              "errors": [],
                              "warnings": [],
                              "subscenarios": []
                            }
                          ]
                        },
                        {
                          "type": "RESULT",
                          "description": "result1 and result2 are the same.",
                          "executions": [
                            {
                              "time": {
                                "start": "YYYY-MM-DDTHH:MM:SS.mmmmmm+HH:MM",
                                "end": "YYYY-MM-DDTHH:MM:SS.mmmmmm+HH:MM",
                                "elapsed": SSS.mmmmmm
                              },
                              "evidence": [
                                "9 == 9"
                              ],
                              "errors": [],
                              "warnings": [],
                              "subscenarios": []
                            }
                          ]
                        }
                      ],
                      "executions": [
                        {
                          "number": 4,
                          "time": {
                            "start": "YYYY-MM-DDTHH:MM:SS.mmmmmm+HH:MM",
                            "end": "YYYY-MM-DDTHH:MM:SS.mmmmmm+HH:MM",
                            "elapsed": SSS.mmmmmm
                          },
                          "errors": [],
                          "warnings": []
                        }
                      ]
                    }
                  ],
                  "status": "SUCCESS",
                  "errors": [],
                  "warnings": [],
                  "time": {
                    "start": "YYYY-MM-DDTHH:MM:SS.mmmmmm+HH:MM",
                    "end": "YYYY-MM-DDTHH:MM:SS.mmmmmm+HH:MM",
                    "elapsed": SSS.mmmmmm
                  }
                }
              ]
            }
          ]
        }
      ],
      "executions": [
        {
          "number": 1,
          "time": {
            "start": "YYYY-MM-DDTHH:MM:SS.mmmmmm+HH:MM",
            "end": "YYYY-MM-DDTHH:MM:SS.mmmmmm+HH:MM",
            "elapsed": SSS.mmmmmm
          },
          "errors": [],
          "warnings": []
        }
      ]
    },
    {
      "location": "demo/commutativeadditions.py:27:CommutativeAdditions.step020",
      "description": "Positive and negative members",
      "reqs": [],
      "actions-results": [
        {
          "type": "ACTION",
          "description": "Launch the CommutativeAddition scenario with -1 and 3 for inputs.",
          "executions": [
            {
              "time": {
                "start": "YYYY-MM-DDTHH:MM:SS.mmmmmm+HH:MM",
                "end": "YYYY-MM-DDTHH:MM:SS.mmmmmm+HH:MM",
                "elapsed": SSS.mmmmmm
              },
              "evidence": [],
              "errors": [],
              "warnings": [],
              "subscenarios": [
                {
                  "name": "demo/commutativeaddition.py",
                  "href": "../../demo/commutativeaddition.py",
                  "attributes": {
                    "TITLE": "Commutative addition",
                    "DESCRIPTION": "Addition of two members, swapping orders."
                  },
                  "reqs": [],
                  "steps": [
                    {
                      "location": "demo/commutativeaddition.py:20:CommutativeAddition.step000",
                      "description": "Initial conditions",
                      "reqs": [],
                      "actions-results": [
                        {
                          "type": "ACTION",
                          "description": "Let a = -1, and b = 3",
                          "executions": [
                            {
                              "time": {
                                "start": "YYYY-MM-DDTHH:MM:SS.mmmmmm+HH:MM",
                                "end": "YYYY-MM-DDTHH:MM:SS.mmmmmm+HH:MM",
                                "elapsed": SSS.mmmmmm
                              },
                              "evidence": [
                                "a = -1",
                                "b = 3"
                              ],
                              "errors": [],
                              "warnings": [],
                              "subscenarios": []
                            }
                          ]
                        }
                      ],
                      "executions": [
                        {
                          "number": 1,
                          "time": {
                            "start": "YYYY-MM-DDTHH:MM:SS.mmmmmm+HH:MM",
                            "end": "YYYY-MM-DDTHH:MM:SS.mmmmmm+HH:MM",
                            "elapsed": SSS.mmmmmm
                          },
                          "errors": [],
                          "warnings": []
                        }
                      ]
                    },
                    {
                      "location": "demo/commutativeaddition.py:27:CommutativeAddition.step010",
                      "description": "a + b",
                      "reqs": [],
                      "actions-results": [
                        {
                          "type": "ACTION",
                          "description": "Compute (a + b) and store the result as result1.",
                          "executions": [
                            {
                              "time": {
                                "start": "YYYY-MM-DDTHH:MM:SS.mmmmmm+HH:MM",
                                "end": "YYYY-MM-DDTHH:MM:SS.mmmmmm+HH:MM",
                                "elapsed": SSS.mmmmmm
                              },
                              "evidence": [
                                "result1 = 2"
                              ],
                              "errors": [],
                              "warnings": [],
                              "subscenarios": []
                            }
                          ]
                        }
                      ],
                      "executions": [
                        {
                          "number": 2,
                          "time": {
                            "start": "YYYY-MM-DDTHH:MM:SS.mmmmmm+HH:MM",
                            "end": "YYYY-MM-DDTHH:MM:SS.mmmmmm+HH:MM",
                            "elapsed": SSS.mmmmmm
                          },
                          "errors": [],
                          "warnings": []
                        }
                      ]
                    },
                    {
                      "location": "demo/commutativeaddition.py:34:CommutativeAddition.step020",
                      "description": "b + a",
                      "reqs": [],
                      "actions-results": [
                        {
                          "type": "ACTION",
                          "description": "Compute (b + a) and store the result as result2.",
                          "executions": [
                            {
                              "time": {
                                "start": "YYYY-MM-DDTHH:MM:SS.mmmmmm+HH:MM",
                                "end": "YYYY-MM-DDTHH:MM:SS.mmmmmm+HH:MM",
                                "elapsed": SSS.mmmmmm
                              },
                              "evidence": [
                                "result2 = 2"
                              ],
                              "errors": [],
                              "warnings": [],
                              "subscenarios": []
                            }
                          ]
                        }
                      ],
                      "executions": [
                        {
                          "number": 3,
                          "time": {
                            "start": "YYYY-MM-DDTHH:MM:SS.mmmmmm+HH:MM",
                            "end": "YYYY-MM-DDTHH:MM:SS.mmmmmm+HH:MM",
                            "elapsed": SSS.mmmmmm
                          },
                          "errors": [],
                          "warnings": []
                        }
                      ]
                    },
                    {
                      "location": "demo/commutativeaddition.py:41:CommutativeAddition.step030",
                      "description": "Check",
                      "reqs": [],
                      "actions-results": [
                        {
                          "type": "ACTION",
                          "description": "Compare result1 and result2.",
                          "executions": [
                            {
                              "time": {
                                "start": "YYYY-MM-DDTHH:MM:SS.mmmmmm+HH:MM",
                                "end": "YYYY-MM-DDTHH:MM:SS.mmmmmm+HH:MM",
                                "elapsed": SSS.mmmmmm
                              },
                              "evidence": [],
                              "errors": [],
                              "warnings": [],
                              "subscenarios": []
                            }
                          ]
                        },
                        {
                          "type": "RESULT",
                          "description": "result1 and result2 are the same.",
                          "executions": [
                            {
                              "time": {
                                "start": "YYYY-MM-DDTHH:MM:SS.mmmmmm+HH:MM",
                                "end": "YYYY-MM-DDTHH:MM:SS.mmmmmm+HH:MM",
                                "elapsed": SSS.mmmmmm
                              },
                              "evidence": [
                                "2 == 2"
                              ],
                              "errors": [],
                              "warnings": [],
                              "subscenarios": []
                            }
                          ]
                        }
                      ],
                      "executions": [
                        {
                          "number": 4,
                          "time": {
                            "start": "YYYY-MM-DDTHH:MM:SS.mmmmmm+HH:MM",
                            "end": "YYYY-MM-DDTHH:MM:SS.mmmmmm+HH:MM",
                            "elapsed": SSS.mmmmmm
                          },
                          "errors": [],
                          "warnings": []
                        }
                      ]
                    }
                  ],
                  "status": "SUCCESS",
                  "errors": [],
                  "warnings": [],
                  "time": {
                    "start": "YYYY-MM-DDTHH:MM:SS.mmmmmm+HH:MM",
                    "end": "YYYY-MM-DDTHH:MM:SS.mmmmmm+HH:MM",
                    "elapsed": SSS.mmmmmm
                  }
                }
              ]
            }
          ]
        }
      ],
      "executions": [
        {
          "number": 2,
          "time": {
            "start": "YYYY-MM-DDTHH:MM:SS.mmmmmm+HH:MM",
            "end": "YYYY-MM-DDTHH:MM:SS.mmmmmm+HH:MM",
            "elapsed": SSS.mmmmmm
          },
          "errors": [],
          "warnings": []
        }
      ]
    },
    {
      "location": "demo/commutativeadditions.py:34:CommutativeAdditions.step030",
      "description": "Both negative members",
      "reqs": [],
      "actions-results": [
        {
          "type": "ACTION",
          "description": "Launch the CommutativeAddition scenario with -1 and -7 for inputs.",
          "executions": [
            {
              "time": {
                "start": "YYYY-MM-DDTHH:MM:SS.mmmmmm+HH:MM",
                "end": "YYYY-MM-DDTHH:MM:SS.mmmmmm+HH:MM",
                "elapsed": SSS.mmmmmm
              },
              "evidence": [],
              "errors": [],
              "warnings": [],
              "subscenarios": [
                {
                  "name": "demo/commutativeaddition.py",
                  "href": "../../demo/commutativeaddition.py",
                  "attributes": {
                    "TITLE": "Commutative addition",
                    "DESCRIPTION": "Addition of two members, swapping orders."
                  },
                  "reqs": [],
                  "steps": [
                    {
                      "location": "demo/commutativeaddition.py:20:CommutativeAddition.step000",
                      "description": "Initial conditions",
                      "reqs": [],
                      "actions-results": [
                        {
                          "type": "ACTION",
                          "description": "Let a = -1, and b = -7",
                          "executions": [
                            {
                              "time": {
                                "start": "YYYY-MM-DDTHH:MM:SS.mmmmmm+HH:MM",
                                "end": "YYYY-MM-DDTHH:MM:SS.mmmmmm+HH:MM",
                                "elapsed": SSS.mmmmmm
                              },
                              "evidence": [
                                "a = -1",
                                "b = -7"
                              ],
                              "errors": [],
                              "warnings": [],
                              "subscenarios": []
                            }
                          ]
                        }
                      ],
                      "executions": [
                        {
                          "number": 1,
                          "time": {
                            "start": "YYYY-MM-DDTHH:MM:SS.mmmmmm+HH:MM",
                            "end": "YYYY-MM-DDTHH:MM:SS.mmmmmm+HH:MM",
                            "elapsed": SSS.mmmmmm
                          },
                          "errors": [],
                          "warnings": []
                        }
                      ]
                    },
                    {
                      "location": "demo/commutativeaddition.py:27:CommutativeAddition.step010",
                      "description": "a + b",
                      "reqs": [],
                      "actions-results": [
                        {
                          "type": "ACTION",
                          "description": "Compute (a + b) and store the result as result1.",
                          "executions": [
                            {
                              "time": {
                                "start": "YYYY-MM-DDTHH:MM:SS.mmmmmm+HH:MM",
                                "end": "YYYY-MM-DDTHH:MM:SS.mmmmmm+HH:MM",
                                "elapsed": SSS.mmmmmm
                              },
                              "evidence": [
                                "result1 = -8"
                              ],
                              "errors": [],
                              "warnings": [],
                              "subscenarios": []
                            }
                          ]
                        }
                      ],
                      "executions": [
                        {
                          "number": 2,
                          "time": {
                            "start": "YYYY-MM-DDTHH:MM:SS.mmmmmm+HH:MM",
                            "end": "YYYY-MM-DDTHH:MM:SS.mmmmmm+HH:MM",
                            "elapsed": SSS.mmmmmm
                          },
                          "errors": [],
                          "warnings": []
                        }
                      ]
                    },
                    {
                      "location": "demo/commutativeaddition.py:34:CommutativeAddition.step020",
                      "description": "b + a",
                      "reqs": [],
                      "actions-results": [
                        {
                          "type": "ACTION",
                          "description": "Compute (b + a) and store the result as result2.",
                          "executions": [
                            {
                              "time": {
                                "start": "YYYY-MM-DDTHH:MM:SS.mmmmmm+HH:MM",
                                "end": "YYYY-MM-DDTHH:MM:SS.mmmmmm+HH:MM",
                                "elapsed": SSS.mmmmmm
                              },
                              "evidence": [
                                "result2 = -8"
                              ],
                              "errors": [],
                              "warnings": [],
                              "subscenarios": []
                            }
                          ]
                        }
                      ],
                      "executions": [
                        {
                          "number": 3,
                          "time": {
                            "start": "YYYY-MM-DDTHH:MM:SS.mmmmmm+HH:MM",
                            "end": "YYYY-MM-DDTHH:MM:SS.mmmmmm+HH:MM",
                            "elapsed": SSS.mmmmmm
                          },
                          "errors": [],
                          "warnings": []
                        }
                      ]
                    },
                    {
                      "location": "demo/commutativeaddition.py:41:CommutativeAddition.step030",
                      "description": "Check",
                      "reqs": [],
                      "actions-results": [
                        {
                          "type": "ACTION",
                          "description": "Compare result1 and result2.",
                          "executions": [
                            {
                              "time": {
                                "start": "YYYY-MM-DDTHH:MM:SS.mmmmmm+HH:MM",
                                "end": "YYYY-MM-DDTHH:MM:SS.mmmmmm+HH:MM",
                                "elapsed": SSS.mmmmmm
                              },
                              "evidence": [],
                              "errors": [],
                              "warnings": [],
                              "subscenarios": []
                            }
                          ]
                        },
                        {
                          "type": "RESULT",
                          "description": "result1 and result2 are the same.",
                          "executions": [
                            {
                              "time": {
                                "start": "YYYY-MM-DDTHH:MM:SS.mmmmmm+HH:MM",
                                "end": "YYYY-MM-DDTHH:MM:SS.mmmmmm+HH:MM",
                                "elapsed": SSS.mmmmmm
                              },
                              "evidence": [
                                "-8 == -8"
                              ],
                              "errors": [],
                              "warnings": [],
                              "subscenarios": []
                            }
                          ]
                        }
                      ],
                      "executions": [
                        {
                          "number": 4,
                          "time": {
                            "start": "YYYY-MM-DDTHH:MM:SS.mmmmmm+HH:MM",
                            "end": "YYYY-MM-DDTHH:MM:SS.mmmmmm+HH:MM",
                            "elapsed": SSS.mmmmmm
                          },
                          "errors": [],
                          "warnings": []
                        }
                      ]
                    }
                  ],
                  "status": "SUCCESS",
                  "errors": [],
                  "warnings": [],
                  "time": {
                    "start": "YYYY-MM-DDTHH:MM:SS.mmmmmm+HH:MM",
                    "end": "YYYY-MM-DDTHH:MM:SS.mmmmmm+HH:MM",
                    "elapsed": SSS.mmmmmm
                  }
                }
              ]
            }
          ]
        }
      ],
      "executions": [
        {
          "number": 3,
          "time": {
            "start": "YYYY-MM-DDTHH:MM:SS.mmmmmm+HH:MM",
            "end": "YYYY-MM-DDTHH:MM:SS.mmmmmm+HH:MM",
            "elapsed": SSS.mmmmmm
          },
          "errors": [],
          "warnings": []
        }
      ]
    }
  ],
  "status": "SUCCESS",
  "errors": [],
  "warnings": [],
  "time": {
    "start": "YYYY-MM-DDTHH:MM:SS.mmmmmm+HH:MM",
    "end": "YYYY-MM-DDTHH:MM:SS.mmmmmm+HH:MM",
    "elapsed": SSS.mmmmmm
  },
  "stats": {
    "steps": {
      "executed": 3,
      "total": 3
    },
    "actions": {
      "executed": 3,
      "total": 3
    },
    "results": {
      "executed": 0,
      "total": 0
    }
  }
}